MANIFEST.in
README.md
setup.py
django_redirect_to_non_www.egg-info/PKG-INFO
django_redirect_to_non_www.egg-info/SOURCES.txt
django_redirect_to_non_www.egg-info/dependency_links.txt
django_redirect_to_non_www.egg-info/requires.txt
django_redirect_to_non_www.egg-info/top_level.txt
redirect_to_non_www/__init__.py
redirect_to_non_www/middleware.py