Metadata-Version: 2.1
Name: django-redirect-to-non-www
Version: 0.1.0
Summary: UNKNOWN
Home-page: UNKNOWN
License: UNKNOWN
Keywords: django redirect www non-www
Platform: UNKNOWN
Classifier: Programming Language :: Python
Classifier: Programming Language :: Python :: 3.5
Classifier: Programming Language :: Python :: 3.6
Classifier: Operating System :: OS Independent
Classifier: Environment :: Web Environment
Classifier: Intended Audience :: Developers
Classifier: Framework :: Django
